CHANGELOG.txt
LICENSE.txt
MANIFEST.in
README.md
requirements.txt
setup.py
tests_requirements.txt
FedPy/__init__.py
FedPy.egg-info/PKG-INFO
FedPy.egg-info/SOURCES.txt
FedPy.egg-info/dependency_links.txt
FedPy.egg-info/requires.txt
FedPy.egg-info/top_level.txt
FedPy/FRED/__init__.py
FedPy/FRED/fred.py
FedPy/Payment_Systems/ACH.py
FedPy/Payment_Systems/Check_Services.py
FedPy/Payment_Systems/Currency.py
FedPy/Payment_Systems/FedWire.py
FedPy/Payment_Systems/National_Settlement_Service.py
FedPy/Payment_Systems/__init__.py
FedPy/Payment_Systems/util.py
FedPy/SOMA_Portfolio/__init__.py
FedPy/SOMA_Portfolio/get_data.py
FedPy/SOMA_Portfolio/soma.py
FedPy/TOMO/__init__.py
FedPy/TOMO/tomo.py
FedPy/publications/__init__.py
FedPy/publications/fomc_statements.py
FedPy/publications/publications.py
FedPy/tests/__init__.py
FedPy/tests/test_FOMC_Statements.py
FedPy/tests/test_Payment_Systems.py
FedPy/tests/test_SOMA.py
FedPy/tests/test_SOMA_links.py
FedPy/tests/test_TOMO.py
FedPy/tests/test_TOMO_links.py
FedPy/tests/test_datesHandler.py
FedPy/util/__init__.py
FedPy/util/date_handler.py
FedPy/util/SOMA/__init__.py
FedPy/util/SOMA/links.py
FedPy/util/TOMO/__init__.py
FedPy/util/TOMO/links.py