Metadata-Version: 2.1
Name: FedPy
Version: 1.1.8
Summary: Fetch official Federal Reserve data for your desired use.
Home-page: https://github.com/antonio-hickey/FedPy
Author: Antonio Hickey
Author-email: antoniohickey99@gmail.com
License: MIT
Keywords: Federal Reserve,Economics,Finance
Platform: UNKNOWN
Classifier: Development Status :: 3 - Alpha
Classifier: License :: OSI Approved :: MIT License
Classifier: Programming Language :: Python :: 3
License-File: LICENSE.txt
